[
  {
    "url": "https://adventuresinparn.blogspot.com/?zx=fdc7c75491a9a92e",
    "title": "Adventures in Parn",
    "description": ""
  },
  {
    "url": "https://kelvingreen.blogspot.com/",
    "title": "Aiee! Run From Kelvin's Brainsplurge!",
    "description": "I'm Kelvin Green. I sometimes draw. I sometimes write. I'm trying to get better at both."
  },
  {
    "url": "https://thealexandrian.net/",
    "title": "The Alexandrian",
    "description": "\u2026designed not only to be a site of news and updates, but also as a repository: Here you\u2019ll find my reviews, my politics, my stories, and my thoughts."
  },
  {
    "url": "https://arsludi.lamemage.com/",
    "title": "ars ludi",
    "description": "if you asked Ben's brain about gaming, this is what it would say."
  },
  {
    "url": "https://direbane.blogspot.com/",
    "title": "Direbane: An RPG Home Brewed Repository",
    "description": "An abode to share artifacts, simulacra, histories, and other items of note related to ongoing years adventuring."
  },
  {
    "url": "https://dreamsinthelichhouse.blogspot.com/",
    "title": "Dreams in the Lich House",
    "description": "A blog about Dungeons & Dragons, Call of Cthulhu, and fantasy and horror gaming."
  },
  {
    "url": "https://www.failuretolerated.com/",
    "title": "Failure Tolerated",
    "description": ""
  },
  {
    "url": "https://goblinshenchman.wordpress.com/",
    "title": "Goblin's Henchman",
    "description": ""
  },
  {
    "url": "https://www.indiegamereadingclub.com/",
    "title": "The Indie Game Reading Club",
    "description": "Deep reads, play analysis, reviews and everything else about small press roleplaying today."
  },
  {
    "url": "https://levellers.blog/",
    "title": "The Levellers",
    "description": ""
  },
  {
    "url": "https://themonstersknow.com",
    "title": "The Monsters Know What They\u2019re Doing",
    "description": "Monster combat tactics for Dungeons & Dragons 5E."
  },
  {
    "url": "https://numbered.works/notes",
    "title": "Numbered Works \u2014 Notes",
    "description": "Making adventures, games, art, toys, music, objects."
  },
  {
    "url": "https://dndwithpornstars.blogspot.com/?zx=4719c95a41276b9e",
    "title": "Playing D&D With Porn Stars",
    "description": "Zak S / Zak Smith / Zak Sabbath playing diy D&D \u2026 notes on playing RPGs w/fellow porn performers."
  },
  {
    "url": "https://profesnpc.blogspot.com/",
    "title": "Professional NPC",
    "description": "Human by day, Dungeon Master by night."
  },
  {
    "url": "https://haikushane.com/",
    "title": "Project Work by Shane Preece",
    "description": "Board game and Dungeons and Dragons development."
  },
  {
    "url": "https://www.rascal.news/",
    "title": "Rascal News",
    "description": "A tabletop roleplaying game and culture outlet."
  },
  {
    "url": "https://rolltop-indigo.blogspot.com/",
    "title": "Rolltop Indigo",
    "description": "The Blue Room Blog: RPGs, Fantasy Cartography, Cooking, Fonts, Stuff."
  },
  {
    "url": "https://save.vs.totalpartykill.ca",
    "title": "Save vs. Total Party Kill",
    "description": "This is a blog about D&D."
  },
  {
    "url": "https://mojobob.blogspot.com/",
    "title": "Shouting Into The Void",
    "description": "Fitz's Roleplaying, Wargaming and Modeling-related blather."
  },
  {
    "url": "https://slyflourish.com/",
    "title": "Sly Flourish: Helping Dungeon Masters run great D&D games.",
    "description": "Weekly articles with tips, tricks, tools, and advice for the ffth edition of Dungeons & Dragons (D&D) written by the author of Return of the Lazy Dungeon Master."
  }
]